ducktools/pytui/__init__.py
ducktools/pytui/__main__.py
ducktools/pytui/_lazy_imports.py
ducktools/pytui/_version.py
ducktools/pytui/commands.py
ducktools/pytui/config.py
ducktools/pytui/platform_paths.py
ducktools/pytui/py.typed
ducktools/pytui/ui.py
ducktools/pytui/runtime_installers/__init__.py
ducktools/pytui/runtime_installers/base.py
ducktools/pytui/runtime_installers/pythoncore.py
ducktools/pytui/runtime_installers/uv.py
ducktools/pytui/shells/__init__.py
ducktools/pytui/shells/_core.py
ducktools/pytui/shells/bash.py
ducktools/pytui/shells/cmd.py
ducktools/pytui/shells/fish.py
ducktools/pytui/shells/powershell.py
ducktools/pytui/shells/zsh.py
ducktools/pytui/shells/scripts/activate_pytui.fish
ducktools/pytui/shells/scripts/activate_pytui.ps1
ducktools/pytui/shells/scripts/activate_pytui.sh
ducktools/pytui/util/__init__.py
ducktools/pytui/util/win32_terminal_hist.py
ducktools_pytui-0.4.4.dist-info/licenses/LICENSE
ducktools_pytui-0.4.4.dist-info/METADATA
ducktools_pytui-0.4.4.dist-info/WHEEL
ducktools_pytui-0.4.4.dist-info/entry_points.txt
ducktools_pytui-0.4.4.dist-info/top_level.txt
ducktools_pytui-0.4.4.dist-info/RECORD
