Metadata-Version: 2.4
Name: ducktools-pytui
Version: 0.4.4
Summary: A TUI for managing Python runtimes and installs
Author: David C Ellis
Project-URL: Homepage, https://github.com/davidcellis/ducktools-pytui
Classifier: Development Status :: 2 - Pre-Alpha
Classifier: Programming Language :: Python :: 3.10
Classifier: Programming Language :: Python :: 3.11
Classifier: Programming Language :: Python :: 3.12
Classifier: Programming Language :: Python :: 3.13
Classifier: Programming Language :: Python :: 3.14
Classifier: License :: OSI Approved :: MIT License
Requires-Python: >=3.10
License-File: LICENSE
Requires-Dist: ducktools-classbuilder>=0.10.0
Requires-Dist: ducktools-pythonfinder>=0.10.0
Requires-Dist: ducktools-lazyimporter>=0.7.3
Requires-Dist: textual>=5.0.1
Dynamic: license-file
